tsoftlib/__init__.py
tsoftlib/api/__init__.py
tsoftlib/api/external_api.py
tsoftlib/api/internal_api.py
tsoftlib/helpers/__init__.py
tsoftlib/helpers/excelReader.py
tsoftlib/helpers/fileMaker.py
tsoftlib/helpers/htmlMaker.py
tsoftlib/helpers/logger.py
tsoftlib/helpers/mailer.py
tsoftlib/helpers/printer.py
tsoftlib/helpers/scheduler.py
tsoftlib-1.0.15.dist-info/LICENSE.txt
tsoftlib-1.0.15.dist-info/METADATA
tsoftlib-1.0.15.dist-info/WHEEL
tsoftlib-1.0.15.dist-info/top_level.txt
tsoftlib-1.0.15.dist-info/RECORD
