Metadata-Version: 2.1
Name: tsoftlib
Version: 1.0.15
Summary: Library for Tsoft API
Home-page: UNKNOWN
Author: Jexulie
Author-email: fejitj3n@yahoo.com
License: UNKNOWN
Platform: UNKNOWN
Classifier: Programming Language :: Python :: 3
Classifier: License :: OSI Approved :: MIT License
Classifier: Operating System :: OS Independent
Requires-Dist: xlrd
Requires-Dist: cx-Oracle
Requires-Dist: dicttoxml
Requires-Dist: xlsxwriter
